{
  "title": "JavaScript Examples",
  "url": "https://www.w3schools.com/js/js_examples.asp",
  "metadata": {
    "viewport": "width=device-width, initial-scale=1",
    "title": "W3Schools.com",
    "Keywords": "HTML, Python, CSS, SQL, JavaScript, How to, PHP, Java, C, C++, C#, jQuery, Bootstrap, Colors, W3.CSS, XML, MySQL, Icons, NodeJS, React, Graphics, Angular, R, AI, Git, Data Science, Code Game, Tutorials, Programming, Web Development, Training, Learning, Quiz, Exercises, Courses, Lessons, References, Examples, Learn to code, Source code, Demos, Tips, Website",
    "Description": "Well organized and easy to understand Web building tutorials with lots of examples of how to use HTML, CSS, JavaScript, SQL, Python, PHP, Bootstrap, Java, XML and more.",
    "og:image": "https://www.w3schools.com/images/w3schools_logo_436_2.png",
    "og:image:type": "image/png",
    "og:image:width": "436",
    "og:image:height": "228",
    "og:description": "W3Schools offers free online tutorials, references and exercises in all the major languages of the web. Covering popular subjects like HTML, CSS, JavaScript, Python, SQL, Java, and many, many more.",
    "msapplication-TileColor": "#00a300",
    "theme-color": "#ffffff",
    "keywords": "HTML, Python, CSS, SQL, JavaScript, How to, PHP, Java, C, C++, C#, jQuery, Bootstrap, Colors, W3.CSS, XML, MySQL, Icons, NodeJS, React, Graphics, Angular, R, AI, Git, Data Science, Code Game, Tutorials, Programming, Web Development, Training, Learning, Quiz, Exercises, Courses, Lessons, References, Examples, Learn to code, Source code, Demos, Tips, Website"
  },
  "content": [
    {
      "type": "header",
      "metadata": {
        "level": "h1"
      },
      "text": "JavaScript Examples",
      "level": "h1"
    },
    {
      "type": "header",
      "metadata": {
        "level": "h2"
      },
      "text": "What can JavaScript do?",
      "level": "h2"
    },
    {
      "type": "text",
      "metadata": {},
      "links": [
        {
          "text": "Examples Explained",
          "href": "https://www.w3schools.com/js_intro.asp",
          "title": ""
        }
      ],
      "text": "Examples Explained",
      "html": "<p><a class=\"ws-btn\" href=\"js_intro.asp\">Examples Explained</a></p>"
    },
    {
      "type": "header",
      "metadata": {
        "level": "h2"
      },
      "text": "Where to Insert JavaScript",
      "level": "h2"
    },
    {
      "type": "text",
      "metadata": {},
      "links": [
        {
          "text": "Where to Explained",
          "href": "https://www.w3schools.com/js_whereto.asp",
          "title": ""
        }
      ],
      "text": "Where to Explained",
      "html": "<p><a class=\"ws-btn\" href=\"js_whereto.asp\">Where to Explained</a></p>"
    },
    {
      "type": "header",
      "metadata": {
        "level": "h2"
      },
      "text": "JavaScript Output",
      "level": "h2"
    },
    {
      "type": "text",
      "metadata": {},
      "links": [
        {
          "text": "Output Explained",
          "href": "https://www.w3schools.com/js_output.asp",
          "title": ""
        }
      ],
      "text": "Output Explained",
      "html": "<p><a class=\"ws-btn\" href=\"js_output.asp\">Output Explained</a></p>"
    },
    {
      "type": "header",
      "metadata": {
        "level": "h2"
      },
      "text": "JavaScript Syntax",
      "level": "h2"
    },
    {
      "type": "text",
      "metadata": {},
      "links": [
        {
          "text": "Syntax Explained",
          "href": "https://www.w3schools.com/js_syntax.asp",
          "title": ""
        }
      ],
      "text": "Syntax Explained",
      "html": "<p><a class=\"ws-btn\" href=\"js_syntax.asp\">Syntax Explained</a></p>"
    },
    {
      "type": "header",
      "metadata": {
        "level": "h2"
      },
      "text": "JavaScript Statements",
      "level": "h2"
    },
    {
      "type": "text",
      "metadata": {},
      "links": [
        {
          "text": "Statements Explained",
          "href": "https://www.w3schools.com/js_statements.asp",
          "title": ""
        }
      ],
      "text": "Statements Explained",
      "html": "<p><a class=\"ws-btn\" href=\"js_statements.asp\">Statements Explained</a></p>"
    },
    {
      "type": "header",
      "metadata": {
        "level": "h2"
      },
      "text": "JavaScript Comments",
      "level": "h2"
    },
    {
      "type": "text",
      "metadata": {},
      "links": [
        {
          "text": "Comments Explained",
          "href": "https://www.w3schools.com/js_comments.asp",
          "title": ""
        }
      ],
      "text": "Comments Explained",
      "html": "<p><a class=\"ws-btn\" href=\"js_comments.asp\">Comments Explained</a></p>"
    },
    {
      "type": "header",
      "metadata": {
        "level": "h2"
      },
      "text": "JavaScript Variables",
      "level": "h2"
    },
    {
      "type": "text",
      "metadata": {},
      "links": [
        {
          "text": "Variables Explained",
          "href": "https://www.w3schools.com/js_variables.asp",
          "title": ""
        }
      ],
      "text": "Variables Explained",
      "html": "<p><a class=\"ws-btn\" href=\"js_variables.asp\">Variables Explained</a></p>"
    },
    {
      "type": "header",
      "metadata": {
        "level": "h2"
      },
      "text": "JavaScript Arithmetic",
      "level": "h2"
    },
    {
      "type": "text",
      "metadata": {},
      "links": [
        {
          "text": "Arithmetic Explained",
          "href": "https://www.w3schools.com/js_arithmetic.asp",
          "title": ""
        }
      ],
      "text": "Arithmetic Explained",
      "html": "<p><a class=\"ws-btn\" href=\"js_arithmetic.asp\">Arithmetic Explained</a></p>"
    },
    {
      "type": "header",
      "metadata": {
        "level": "h2"
      },
      "text": "JavaScript Assignment",
      "level": "h2"
    },
    {
      "type": "text",
      "metadata": {},
      "links": [
        {
          "text": "Assignment Explained",
          "href": "https://www.w3schools.com/js_assignment.asp",
          "title": ""
        }
      ],
      "text": "Assignment Explained",
      "html": "<p><a class=\"ws-btn\" href=\"js_assignment.asp\">Assignment Explained</a></p>"
    },
    {
      "type": "header",
      "metadata": {
        "level": "h2"
      },
      "text": "JavaScript String Concatenation",
      "level": "h2"
    },
    {
      "type": "text",
      "metadata": {},
      "links": [
        {
          "text": "Concatenation Explained",
          "href": "https://www.w3schools.com/js_operators.asp",
          "title": ""
        }
      ],
      "text": "Concatenation Explained",
      "html": "<p><a class=\"ws-btn\" href=\"js_operators.asp\">Concatenation Explained</a></p>"
    },
    {
      "type": "header",
      "metadata": {
        "level": "h2"
      },
      "text": "JavaScript Data Types",
      "level": "h2"
    },
    {
      "type": "text",
      "metadata": {},
      "links": [
        {
          "text": "Data types Explained",
          "href": "https://www.w3schools.com/js_datatypes.asp",
          "title": ""
        }
      ],
      "text": "Data types Explained",
      "html": "<p>\n<a class=\"ws-btn\" href=\"js_datatypes.asp\">Data types Explained</a></p>"
    },
    {
      "type": "header",
      "metadata": {
        "level": "h2"
      },
      "text": "JavaScript Objects",
      "level": "h2"
    },
    {
      "type": "text",
      "metadata": {},
      "links": [
        {
          "text": "Objects Explained",
          "href": "https://www.w3schools.com/js_objects.asp",
          "title": ""
        }
      ],
      "text": "Objects Explained",
      "html": "<p>\n<a class=\"ws-btn\" href=\"js_objects.asp\">Objects Explained</a></p>"
    },
    {
      "type": "header",
      "metadata": {
        "level": "h2"
      },
      "text": "JavaScript Functions",
      "level": "h2"
    },
    {
      "type": "text",
      "metadata": {},
      "links": [
        {
          "text": "Functions Explained",
          "href": "https://www.w3schools.com/js_functions.asp",
          "title": ""
        }
      ],
      "text": "Functions Explained",
      "html": "<p><a class=\"ws-btn\" href=\"js_functions.asp\">Functions Explained</a></p>"
    },
    {
      "type": "header",
      "metadata": {
        "level": "h2"
      },
      "text": "JavaScript Events",
      "level": "h2"
    },
    {
      "type": "text",
      "metadata": {},
      "links": [
        {
          "text": "Events Explained",
          "href": "https://www.w3schools.com/js_events.asp",
          "title": ""
        }
      ],
      "text": "Events Explained",
      "html": "<p><a class=\"ws-btn\" href=\"js_events.asp\">Events Explained</a></p>"
    },
    {
      "type": "header",
      "metadata": {
        "level": "h2"
      },
      "text": "JavaScript Strings",
      "level": "h2"
    },
    {
      "type": "text",
      "metadata": {},
      "links": [
        {
          "text": "Strings Explained",
          "href": "https://www.w3schools.com/js_strings.asp",
          "title": ""
        }
      ],
      "text": "Strings Explained",
      "html": "<p><a class=\"ws-btn\" href=\"js_strings.asp\">Strings Explained</a></p>"
    },
    {
      "type": "header",
      "metadata": {
        "level": "h2"
      },
      "text": "JavaScript Numbers",
      "level": "h2"
    },
    {
      "type": "text",
      "metadata": {},
      "links": [
        {
          "text": "Numbers Explained",
          "href": "https://www.w3schools.com/js_numbers.asp",
          "title": ""
        }
      ],
      "text": "Numbers Explained",
      "html": "<p><a class=\"ws-btn\" href=\"js_numbers.asp\">Numbers Explained</a></p>"
    },
    {
      "type": "header",
      "metadata": {
        "level": "h2"
      },
      "text": "JavaScript Number Methods",
      "level": "h2"
    },
    {
      "type": "text",
      "metadata": {},
      "links": [
        {
          "text": "Numbers Methods Explained",
          "href": "https://www.w3schools.com/js_number_methods.asp",
          "title": ""
        }
      ],
      "text": "Numbers Methods Explained",
      "html": "<p><a class=\"ws-btn\" href=\"js_number_methods.asp\">Numbers Methods Explained</a></p>"
    },
    {
      "type": "header",
      "metadata": {
        "level": "h2"
      },
      "text": "JavaScript Maths",
      "level": "h2"
    },
    {
      "type": "text",
      "metadata": {},
      "links": [
        {
          "text": "Maths Explained",
          "href": "https://www.w3schools.com/js_math.asp",
          "title": ""
        }
      ],
      "text": "Maths Explained",
      "html": "<p><a class=\"ws-btn\" href=\"js_math.asp\">Maths Explained</a></p>"
    },
    {
      "type": "header",
      "metadata": {
        "level": "h2"
      },
      "text": "JavaScript Random",
      "level": "h2"
    },
    {
      "type": "text",
      "metadata": {},
      "links": [
        {
          "text": "Random Explained",
          "href": "https://www.w3schools.com/js_random.asp",
          "title": ""
        }
      ],
      "text": "Random Explained",
      "html": "<p>\n<a class=\"ws-btn\" href=\"js_random.asp\">Random Explained</a></p>"
    },
    {
      "type": "header",
      "metadata": {
        "level": "h2"
      },
      "text": "JavaScript Dates",
      "level": "h2"
    },
    {
      "type": "text",
      "metadata": {},
      "links": [
        {
          "text": "Dates Explained",
          "href": "https://www.w3schools.com/js_dates.asp",
          "title": ""
        }
      ],
      "text": "Dates Explained",
      "html": "<p><a class=\"ws-btn\" href=\"js_dates.asp\">Dates Explained</a></p>"
    },
    {
      "type": "header",
      "metadata": {
        "level": "h2"
      },
      "text": "JavaScript Arrays",
      "level": "h2"
    },
    {
      "type": "text",
      "metadata": {},
      "links": [
        {
          "text": "Arrays Explained",
          "href": "https://www.w3schools.com/js_arrays.asp",
          "title": ""
        }
      ],
      "text": "Arrays Explained",
      "html": "<p><a class=\"ws-btn\" href=\"js_arrays.asp\">Arrays Explained</a></p>"
    },
    {
      "type": "header",
      "metadata": {
        "level": "h2"
      },
      "text": "JavaScript Array Methods",
      "level": "h2"
    },
    {
      "type": "text",
      "metadata": {},
      "links": [
        {
          "text": "Array Methods Explained",
          "href": "https://www.w3schools.com/js_array_methods.asp",
          "title": ""
        }
      ],
      "text": "Array Methods Explained",
      "html": "<p><a class=\"ws-btn\" href=\"js_array_methods.asp\">Array Methods Explained</a></p>"
    },
    {
      "type": "header",
      "metadata": {
        "level": "h2"
      },
      "text": "JavaScript Array Sort",
      "level": "h2"
    },
    {
      "type": "text",
      "metadata": {},
      "links": [
        {
          "text": "Array Sort Explained",
          "href": "https://www.w3schools.com/js_array_sort.asp",
          "title": ""
        }
      ],
      "text": "Array Sort Explained",
      "html": "<p><a class=\"ws-btn\" href=\"js_array_sort.asp\">Array Sort Explained</a></p>"
    },
    {
      "type": "header",
      "metadata": {
        "level": "h2"
      },
      "text": "JavaScript Array Iteration",
      "level": "h2"
    },
    {
      "type": "text",
      "metadata": {},
      "links": [
        {
          "text": "Array Iteration Explained",
          "href": "https://www.w3schools.com/js_array_iteration.asp",
          "title": ""
        }
      ],
      "text": "Array Iteration Explained",
      "html": "<p><a class=\"ws-btn\" href=\"js_array_iteration.asp\">Array Iteration Explained</a></p>"
    },
    {
      "type": "header",
      "metadata": {
        "level": "h2"
      },
      "text": "JavaScript Type Conversion",
      "level": "h2"
    },
    {
      "type": "text",
      "metadata": {},
      "links": [
        {
          "text": "Type Conversion Explained",
          "href": "https://www.w3schools.com/js_type_conversion.asp",
          "title": ""
        }
      ],
      "text": "Type Conversion Explained",
      "html": "<p><a class=\"ws-btn\" href=\"js_type_conversion.asp\">Type Conversion Explained</a></p>"
    },
    {
      "type": "header",
      "metadata": {
        "level": "h2"
      },
      "text": "JavaScript Booleans",
      "level": "h2"
    },
    {
      "type": "text",
      "metadata": {},
      "links": [
        {
          "text": "Booleans Explained",
          "href": "https://www.w3schools.com/js_booleans.asp",
          "title": ""
        }
      ],
      "text": "Booleans Explained",
      "html": "<p><a class=\"ws-btn\" href=\"js_booleans.asp\">Booleans Explained</a></p>"
    },
    {
      "type": "header",
      "metadata": {
        "level": "h2"
      },
      "text": "JavaScript Comparisons",
      "level": "h2"
    },
    {
      "type": "text",
      "metadata": {},
      "links": [
        {
          "text": "Comparisons Explained",
          "href": "https://www.w3schools.com/js_comparisons.asp",
          "title": ""
        }
      ],
      "text": "Comparisons Explained",
      "html": "<p><a class=\"ws-btn\" href=\"js_comparisons.asp\">Comparisons Explained</a></p>"
    },
    {
      "type": "header",
      "metadata": {
        "level": "h2"
      },
      "text": "JavaScript Conditionals",
      "level": "h2"
    },
    {
      "type": "text",
      "metadata": {},
      "links": [
        {
          "text": "Conditionals Explained",
          "href": "https://www.w3schools.com/js_if_else.asp",
          "title": ""
        }
      ],
      "text": "Conditionals Explained",
      "html": "<p><a class=\"ws-btn\" href=\"js_if_else.asp\">Conditionals Explained</a></p>"
    },
    {
      "type": "header",
      "metadata": {
        "level": "h2"
      },
      "text": "JavaScript Loops",
      "level": "h2"
    },
    {
      "type": "text",
      "metadata": {},
      "links": [
        {
          "text": "Loops Explained",
          "href": "https://www.w3schools.com/js_loop_for.asp",
          "title": ""
        }
      ],
      "text": "Loops Explained",
      "html": "<p><a class=\"ws-btn\" href=\"js_loop_for.asp\">Loops Explained</a></p>"
    },
    {
      "type": "header",
      "metadata": {
        "level": "h2"
      },
      "text": "JavaScript Error Handling",
      "level": "h2"
    },
    {
      "type": "text",
      "metadata": {},
      "links": [
        {
          "text": "Errors Explained",
          "href": "https://www.w3schools.com/js_errors.asp",
          "title": ""
        }
      ],
      "text": "Errors Explained",
      "html": "<p><a class=\"ws-btn\" href=\"js_errors.asp\">Errors Explained</a></p>"
    },
    {
      "type": "header",
      "metadata": {
        "level": "h2"
      },
      "text": "JavaScript Regular Expressions",
      "level": "h2"
    },
    {
      "type": "text",
      "metadata": {},
      "links": [
        {
          "text": "Regular Expressions Explained",
          "href": "https://www.w3schools.com/js_regexp.asp",
          "title": ""
        }
      ],
      "text": "Regular Expressions Explained",
      "html": "<p><a class=\"ws-btn\" href=\"js_regexp.asp\">Regular Expressions Explained</a>\n</p>"
    },
    {
      "type": "header",
      "metadata": {
        "level": "h2"
      },
      "text": "JavaScript Objects",
      "level": "h2"
    },
    {
      "type": "text",
      "metadata": {},
      "links": [
        {
          "text": "Objects Explained",
          "href": "https://www.w3schools.com/js_object_definition.asp",
          "title": ""
        }
      ],
      "text": "Objects Explained",
      "html": "<p><a class=\"ws-btn\" href=\"js_object_definition.asp\">Objects Explained</a></p>"
    },
    {
      "type": "header",
      "metadata": {
        "level": "h2"
      },
      "text": "JavaScript Object Properties",
      "level": "h2"
    },
    {
      "type": "text",
      "metadata": {},
      "links": [
        {
          "text": "Object Properties Explained",
          "href": "https://www.w3schools.com/js_object_properties.asp",
          "title": ""
        }
      ],
      "text": "Object Properties Explained",
      "html": "<p><a class=\"ws-btn\" href=\"js_object_properties.asp\">Object Properties Explained</a></p>"
    },
    {
      "type": "header",
      "metadata": {
        "level": "h2"
      },
      "text": "JSON Objects",
      "level": "h2"
    },
    {
      "type": "text",
      "metadata": {},
      "links": [
        {
          "text": "JSON Object Properties Explained",
          "href": "https://www.w3schools.com/js_json_objects.asp",
          "title": ""
        }
      ],
      "text": "JSON Object Properties Explained",
      "html": "<p><a class=\"ws-btn\" href=\"js_json_objects.asp\">JSON Object Properties Explained</a></p>"
    },
    {
      "type": "header",
      "metadata": {
        "level": "h2"
      },
      "text": "JSON Arrays",
      "level": "h2"
    },
    {
      "type": "text",
      "metadata": {},
      "links": [
        {
          "text": "JSON Arrays Explained",
          "href": "https://www.w3schools.com/js_json_arrays.asp",
          "title": ""
        }
      ],
      "text": "JSON Arrays Explained",
      "html": "<p><a class=\"ws-btn\" href=\"js_json_arrays.asp\">JSON Arrays Explained</a></p>"
    },
    {
      "type": "header",
      "metadata": {
        "level": "h2"
      },
      "text": "JSON Parse",
      "level": "h2"
    },
    {
      "type": "text",
      "metadata": {},
      "links": [
        {
          "text": "JSON Parse Explained",
          "href": "https://www.w3schools.com/js_json_parse.asp",
          "title": ""
        }
      ],
      "text": "JSON Parse Explained",
      "html": "<p><a class=\"ws-btn\" href=\"js_json_parse.asp\">JSON Parse Explained</a></p>"
    },
    {
      "type": "header",
      "metadata": {
        "level": "h2"
      },
      "text": "JSON Stringify",
      "level": "h2"
    },
    {
      "type": "text",
      "metadata": {},
      "links": [
        {
          "text": "JSON Stringify Explained",
          "href": "https://www.w3schools.com/js_json_stringify.asp",
          "title": ""
        }
      ],
      "text": "JSON Stringify Explained",
      "html": "<p><a class=\"ws-btn\" href=\"js_json_stringify.asp\">JSON Stringify Explained</a></p>"
    },
    {
      "type": "header",
      "metadata": {
        "level": "h2"
      },
      "text": "JSON PHP",
      "level": "h2"
    },
    {
      "type": "text",
      "metadata": {},
      "links": [
        {
          "text": "JSON PHP Explained",
          "href": "https://www.w3schools.com/js_json_php.asp",
          "title": ""
        }
      ],
      "text": "JSON PHP Explained",
      "html": "<p><a class=\"ws-btn\" href=\"js_json_php.asp\">JSON PHP Explained</a></p>"
    },
    {
      "type": "header",
      "metadata": {
        "level": "h2"
      },
      "text": "JSON HTML",
      "level": "h2"
    },
    {
      "type": "text",
      "metadata": {},
      "links": [
        {
          "text": "JSON HTML Explained",
          "href": "https://www.w3schools.com/js_json_html.asp",
          "title": ""
        }
      ],
      "text": "JSON HTML Explained",
      "html": "<p><a class=\"ws-btn\" href=\"js_json_html.asp\">JSON HTML Explained</a></p>"
    },
    {
      "type": "header",
      "metadata": {
        "level": "h2"
      },
      "text": "JSON JSONP",
      "level": "h2"
    },
    {
      "type": "text",
      "metadata": {},
      "links": [
        {
          "text": "JSON JSONP Explained",
          "href": "https://www.w3schools.com/js_json_jsonp.asp",
          "title": ""
        }
      ],
      "text": "JSON JSONP Explained",
      "html": "<p><a class=\"ws-btn\" href=\"js_json_jsonp.asp\">JSON JSONP Explained</a></p>"
    }
  ]
}