{
  "id": "41fe1b43-031b-4b05-a363-d5499d301620",
  "title": "CSSHeight, Width and Max-width",
  "slug": "cssheight-width-and-max-width",
  "metadata": {
    "description": "Learn about CSSHeight, Width and Max-width with clear explanations and practical examples.",
    "keywords": [
      "c",
      "width",
      "height",
      "element",
      "property",
      "pixels",
      "sets",
      "maximum",
      "example",
      "properties",
      "value"
    ],
    "difficulty": "beginner",
    "prerequisites": [
      "C Basics"
    ],
    "estimated_time": 5,
    "category": "LearnCSS",
    "subcategory": "CSS Height/Width"
  },
  "content_sections": [
    {
      "type": "introduction",
      "title": "Introduction",
      "content": "CSS\nHeight, Width and Max-width",
      "order": 1,
      "code": null,
      "language": null,
      "explanation": null
    },
    {
      "type": "concept",
      "title": "Details",
      "content": "The CSS\nheight\nand\nwidth\nproperties are used to set the \nheight and width of an element.\nThe CSS\nmax-width\nproperty is used to set the maximum width of an element.\nThis element has a height of 50 pixels and a width of 100%.\n\nCSS Setting height and width\nThe\nheight\nand\nwidth\nproperties are used to set the \nheight and width of an element.\nThe height and width properties do not include padding, borders, or margins. \nIt sets the height/width of the area inside the padding, border, and margin of \nthe element.\nCSS height and width Values\nThe\nheight\nand\nwidth\nproperties \nmay have the following values:\nauto\n- This is default. The browser \ncalculates the height and width\nlength\n- Defines the height/width in px, cm, \netc.\n%\n- Defines the height/width in percent of \nthe containing block\ninitial\n- Sets the height/width to its \ndefault value\ninherit\n- The height/width will be \n  inherited from its parent value\nCSS height and width Examples\nThis element has a height of 200 pixels and a width of 50%\nExample\nSet the height and width of a <div> element:\ndiv {\nheight: \n200px;\nwidth: 50%;\nbackground-color: powderblue;\n}\n\nThis element has a height of 100 pixels and a width of 500 pixels.\nExample\nSet the height and width of another <div> element:\ndiv {\nheight: \n100px;\nwidth: 500px;\nbackground-color: powderblue;\n}\n\nNote:\nRemember that the\nheight\nand\nwidth\nproperties do not include padding, borders, \nor margins! They set the height/width of the area inside the padding, border, \nand margin of the element!\nSetting max-width\nThe\nmax-width\nproperty is used to set the maximum width of an element.\nThe\nmax-width\ncan be specified in\nlength values\n, like px, cm, etc., or in percent (%) of the \ncontaining block, or set to none (this is \ndefault. Means that there is no maximum width).\nThe problem with the\n<div>\nabove occurs when the browser window is smaller than the width of \nthe element (500px). The browser then adds a horizontal scrollbar to the page.\nIn this situation, using\nmax-width\nwill improve the browser's handling of small windows.\nTip:\nDrag the browser window to smaller than 500px wide, to see the difference between \nthe two divs!\nThis element has a height of 100 pixels and a max-width of 500 pixels.\nNote:\nIf you for some reason use both the\nwidth\nproperty and the\nmax-width\nproperty on the same element, and the value of the\nwidth\nproperty is larger than the\nmax-width\nproperty; the\nmax-width\nproperty will be used (and the\nwidth\nproperty will be ignored).\nExample\nThis <div> element has a height of 100 pixels and a \nmax-width of 500 pixels:\ndiv {\nmax-width: 500px;\nheight: \n100px;\nbackground-color: powderblue;\n}\n\nSet the height and width of elements\nThis example demonstrates how to set the height and width of different elements.\nSet the height and width of an image using percent\nThis example demonstrates how to set the height and width of an image using a percent value.\nSet min-width and max-width of an element\nThis example demonstrates how to set a minimum width and a maximum width of an element using a pixel value.\nSet min-height and max-height of an element\nThis example demonstrates how to set a minimum height and a maximum height of an element using a pixel value.\nAll CSS Dimension Properties\nProperty\nDescription\nheight\nSets the height of an element\nmax-height\nSets the maximum height of an element\nmax-width\nSets the maximum width of an element\nmin-height\nSets the minimum height of an element\nmin-width\nSets the minimum width of an element\nwidth\nSets the width of an element\n\n\u2605\n+1",
      "order": 2,
      "code": null,
      "language": null,
      "explanation": null
    },
    {
      "type": "code_example",
      "title": "Example",
      "content": "",
      "order": 3,
      "code": "div {\nheight: \n200px;\nwidth: 50%;\nbackground-color: powderblue;\n}",
      "language": "css",
      "explanation": "Example of example"
    },
    {
      "type": "code_example",
      "title": "Example",
      "content": "",
      "order": 4,
      "code": "div {\nheight: \n100px;\nwidth: 500px;\nbackground-color: powderblue;\n}",
      "language": "css",
      "explanation": "Example of example"
    },
    {
      "type": "code_example",
      "title": "Example",
      "content": "",
      "order": 5,
      "code": "div {\nmax-width: 500px;\nheight: \n100px;\nbackground-color: powderblue;\n}",
      "language": "css",
      "explanation": "Example of example"
    }
  ],
  "practice_exercises": [
    {
      "title": "Complete the Code 1",
      "description": "Fill in the missing line to make this code work.",
      "difficulty": "medium",
      "starter_code": "div {\n# TODO: Complete this line\n200px;\nwidth: 50%;\nbackground-color: powderblue;\n}",
      "solution": "div {\nheight: \n200px;\nwidth: 50%;\nbackground-color: powderblue;\n}"
    },
    {
      "title": "Complete the Code 2",
      "description": "Fill in the missing line to make this code work.",
      "difficulty": "medium",
      "starter_code": "div {\nheight: \n100px;\nwidth: 500px;\n# TODO: Complete this line\n}",
      "solution": "div {\nheight: \n100px;\nwidth: 500px;\nbackground-color: powderblue;\n}"
    }
  ],
  "related_topics": [
    {
      "id": "2859fff4-a466-4879-ac68-8bc8f5af0b0d",
      "title": "C Best Practices",
      "relationship": "related_topic"
    },
    {
      "id": "3826e26c-02df-4a7e-8594-51b3aa1bbfcc",
      "title": "C Common Pitfalls and How to Avoid Them",
      "relationship": "suggested_reading"
    },
    {
      "id": "2461c7c4-71eb-4310-ac06-8c1126be955a",
      "title": "C Fundamentals",
      "relationship": "prerequisite"
    }
  ],
  "quiz": [
    {
      "question": "What is width\n\nThe CSS\nheight\nand\nwidth\nproperties?",
      "options": [
        "used to set the \nheight and width of an element",
        "None of the above.",
        "used to set the maximum width of an element",
        "None of the above."
      ],
      "correct_answer": 0,
      "explanation": "The correct definition of width\n\nThe CSS\nheight\nand\nwidth\nproperties is 'used to set the \nheight and width of an element'."
    },
    {
      "question": "What is width\nproperty?",
      "options": [
        "used to set the \nheight and width of an element",
        "used to set the maximum width of an element",
        "None of the above.",
        "None of the above."
      ],
      "correct_answer": 1,
      "explanation": "The correct definition of width\nproperty is 'used to set the maximum width of an element'."
    }
  ],
  "summary": "This tutorial covers CSSHeight, Width and Max-width concepts and techniques. You'll learn how to use CSSHeight, Width and Max-width effectively, including key principles, common patterns, and practical examples. By the end of this tutorial, you'll have a solid understanding of CSSHeight, Width and Max-width and how to apply it in your projects."
}