{
  "title": "How To Create Image Hover Overlay Effects",
  "url": "https://www.w3schools.com/howto/howto_css_image_overlay.asp",
  "metadata": {
    "viewport": "width=device-width, initial-scale=1",
    "title": "W3Schools.com",
    "Keywords": "HTML, Python, CSS, SQL, JavaScript, How to, PHP, Java, C, C++, C#, jQuery, Bootstrap, Colors, W3.CSS, XML, MySQL, Icons, NodeJS, React, Graphics, Angular, R, AI, Git, Data Science, Code Game, Tutorials, Programming, Web Development, Training, Learning, Quiz, Exercises, Courses, Lessons, References, Examples, Learn to code, Source code, Demos, Tips, Website",
    "Description": "Well organized and easy to understand Web building tutorials with lots of examples of how to use HTML, CSS, JavaScript, SQL, Python, PHP, Bootstrap, Java, XML and more.",
    "og:image": "https://www.w3schools.com/images/w3schools_logo_436_2.png",
    "og:image:type": "image/png",
    "og:image:width": "436",
    "og:image:height": "228",
    "og:description": "W3Schools offers free online tutorials, references and exercises in all the major languages of the web. Covering popular subjects like HTML, CSS, JavaScript, Python, SQL, Java, and many, many more.",
    "msapplication-TileColor": "#00a300",
    "theme-color": "#ffffff",
    "keywords": "HTML, Python, CSS, SQL, JavaScript, How to, PHP, Java, C, C++, C#, jQuery, Bootstrap, Colors, W3.CSS, XML, MySQL, Icons, NodeJS, React, Graphics, Angular, R, AI, Git, Data Science, Code Game, Tutorials, Programming, Web Development, Training, Learning, Quiz, Exercises, Courses, Lessons, References, Examples, Learn to code, Source code, Demos, Tips, Website"
  },
  "content": [
    {
      "type": "header",
      "metadata": {
        "level": "h1"
      },
      "text": "How TO - Image Hover Overlay",
      "level": "h1"
    },
    {
      "type": "text",
      "metadata": {},
      "text": "Learn how to create image overlay hover effects.",
      "html": "<p class=\"intro\">Learn how to create image overlay hover effects.</p>"
    },
    {
      "type": "header",
      "metadata": {
        "level": "h2"
      },
      "text": "Image Overlay Fade",
      "level": "h2"
    },
    {
      "type": "text",
      "metadata": {},
      "text": "Learn how to create a fading overlay effect to an image, on hover:",
      "html": "<p>Learn how to create a fading overlay effect to an image, on hover:</p>"
    },
    {
      "type": "code",
      "metadata": {
        "language": "unknown",
        "tryItLink": null,
        "syntaxHighlighting": [],
        "classList": [
          "w3-example"
        ],
        "isNotranslate": false
      },
      "images": [
        {
          "src": "/w3css/img_avatar3.png",
          "alt": "Avatar",
          "title": "",
          "local_path": "/home/ziko/Dev/Scraper/assets/howto/img_avatar3.png"
        }
      ],
      "code": "Example Fade in text: Hello World Try it Yourself \u00bb",
      "language": "unknown",
      "tryItLink": null,
      "syntax_highlighting_data": [],
      "class_list": [
        "w3-example"
      ],
      "is_notranslate": false
    },
    {
      "type": "code",
      "metadata": {
        "language": "unknown",
        "tryItLink": null,
        "syntaxHighlighting": [],
        "classList": [
          "w3-example"
        ],
        "isNotranslate": false
      },
      "images": [
        {
          "src": "/w3css/img_avatar3.png",
          "alt": "Avatar",
          "title": "",
          "local_path": "/home/ziko/Dev/Scraper/assets/howto/img_avatar3.png"
        }
      ],
      "code": "Example Fade in a box: John Try it Yourself \u00bb",
      "language": "unknown",
      "tryItLink": null,
      "syntax_highlighting_data": [],
      "class_list": [
        "w3-example"
      ],
      "is_notranslate": false
    },
    {
      "type": "text",
      "metadata": {},
      "links": [
        {
          "text": "CSS Images Tutorial",
          "href": "https://www.w3schools.com/css/css3_images.asp",
          "title": ""
        }
      ],
      "text": "Tip: Go to our CSS Images Tutorial to learn more about how to style images.",
      "html": "<p><strong>Tip:</strong> Go to our <a href=\"/css/css3_images.asp\">CSS Images Tutorial</a> to learn \nmore about how to style images.</p>"
    },
    {
      "type": "text",
      "metadata": {},
      "links": [
        {
          "text": "Image Overlay Slide",
          "href": "https://www.w3schools.com/howto_css_image_overlay_slide.asp",
          "title": ""
        },
        {
          "text": "Image Overlay Zoom",
          "href": "https://www.w3schools.com/howto_css_image_overlay_zoom.asp",
          "title": ""
        },
        {
          "text": "Image Overlay Title",
          "href": "https://www.w3schools.com/howto_css_image_overlay_title.asp",
          "title": ""
        },
        {
          "text": "Image Overlay Icon",
          "href": "https://www.w3schools.com/howto_css_image_overlay_icon.asp",
          "title": ""
        }
      ],
      "text": "Also check out: Image Overlay Slide , Image Overlay Zoom , Image Overlay Title and Image Overlay Icon .",
      "html": "<p>Also check out: <a href=\"howto_css_image_overlay_slide.asp\">Image Overlay Slide</a>, <a href=\"howto_css_image_overlay_zoom.asp\">Image Overlay Zoom</a>, <a href=\"howto_css_image_overlay_title.asp\">Image Overlay Title</a> and <a href=\"howto_css_image_overlay_icon.asp\">Image Overlay Icon</a>.</p>"
    }
  ]
}